qsct/__init__.py
qsct/functions.py
qsct/main.py
qsct/obj_method.py
tests/__init__.py
tests/listener_test.py
tests/send_test.py
tests/test_functions.py
tests/test_obj_serv.py
tests/tets_obj_send.py
qsct-0.95.dist-info/LICENSE
qsct-0.95.dist-info/METADATA
qsct-0.95.dist-info/WHEEL
qsct-0.95.dist-info/top_level.txt
qsct-0.95.dist-info/RECORD
