Metadata-Version: 2.1
Name: qsct
Version: 0.95
Author: PunchyArchy
Author-email: ksmdrmvscthny@gmail.com
License-File: LICENSE
